{
  "configurations": [
    {
      "browse": {
        "databaseFilename": "${default}",
        "limitSymbolsToIncludedHeaders": false
      },
      "includePath": [
        "/home/maryam/Documents/devel/include/**",
        "/opt/ros/noetic/include/**",
        "/home/maryam/Documents/src/rosserial/rosserial_server/include/**",
        "/home/maryam/Documents/src/rosserial/rosserial_test/include/**",
        "/usr/include/**"
      ],
      "name": "ROS",
      "intelliSenseMode": "gcc-x64",
      "compilerPath": "/usr/bin/gcc",
      "cStandard": "gnu11",
      "cppStandard": "c++14"
    }
  ],
  "version": 4
}